kabbes_cryptography/AES.py
kabbes_cryptography/Combined.py
kabbes_cryptography/RSA.py
kabbes_cryptography/__init__.py
kabbes_cryptography/__main__.py
kabbes_cryptography-0.1.0.dist-info/LICENSE
kabbes_cryptography-0.1.0.dist-info/METADATA
kabbes_cryptography-0.1.0.dist-info/WHEEL
kabbes_cryptography-0.1.0.dist-info/top_level.txt
kabbes_cryptography-0.1.0.dist-info/RECORD
