Metadata-Version: 2.1
Name: kabbes-cryptography
Version: 0.1.0
Summary: Easy implementation of professional Python cryptography packages
Home-page: https://pypi.org/project/kabbes-cryptography
Author: James Kabbes
Author-email: james.kabbes@gmail.com
Project-URL: GitHub, https://github.com/jameskabbes/kabbes_cryptography
Project-URL: Documentation, https://jameskabbes.github.io/cryptography
Classifier: Programming Language :: Python :: 3
Classifier: License :: OSI Approved :: MIT License
Classifier: Operating System :: OS Independent
Requires-Python: >=3.7
License-File: LICENSE
Requires-Dist: pycryptodome
Requires-Dist: rsa
Requires-Dist: kabbes-dir-ops
Requires-Dist: kabbes-parent-class
Requires-Dist: kabbes-py-starter
